tietoolbox/__init__.py
tietoolbox/commonlogger.py
tietoolbox/config.py
tietoolbox/feature_exporter.py
tietoolbox/runner.py
tietoolbox/utils.py
tietoolbox/data/config.json
tietoolbox/data/geocover.gdb.zip
tietoolbox/data/run.bat
tietoolbox/data/swissalti3d-2.0-mosaic.tif
tietoolbox/data/cache/BEDrst.npy
tietoolbox/data/cache/BEDrst.tif
tietoolbox/data/cache/Bedrock_HARMOS_lt40000_Extract.geojson
tietoolbox/data/cache/DEM.pkl
tietoolbox/data/cache/Linear_Objects.geojson
tietoolbox/data/cache/TECrst.npy
tietoolbox/data/cache/TECrst.tif
tietoolbox/data/cache/cropped.tif
tietoolbox/data/cache/extent.geojson
tietoolbox/data/cache/extent.pkl
tietoolbox/data/cache/faults.pkl
tietoolbox/data/cache/traces.pkl
tietoolbox/esri/toolboxes/TIEtoolbox.Analysis.pyt.xml
tietoolbox/esri/toolboxes/TIEtoolbox.Downloader.pyt.xml
tietoolbox/esri/toolboxes/TIEtoolbox.Exporter.pyt.xml
tietoolbox/esri/toolboxes/TIEtoolbox.Viewer.pyt.xml
tietoolbox/esri/toolboxes/TIEtoolbox.pyt
tietoolbox/esri/toolboxes/TIEtoolbox.pyt.xml
tietoolbox/scripts/__init__.py
tietoolbox/scripts/config.py
tietoolbox/scripts/symbols.tsv
tietoolbox/scripts/tie_analysis_dask.py
tietoolbox/scripts/tie_demo.py
tietoolbox/scripts/tie_viewer.py
tietoolbox/scripts/traces_export_utils.py
tietoolbox/scripts/utils.py
tietoolbox-0.4.11.dist-info/LICENSE.txt
tietoolbox-0.4.11.dist-info/METADATA
tietoolbox-0.4.11.dist-info/WHEEL
tietoolbox-0.4.11.dist-info/entry_points.txt
tietoolbox-0.4.11.dist-info/top_level.txt
tietoolbox-0.4.11.dist-info/RECORD
