Metadata-Version: 2.1
Name: tietoolbox
Version: 0.4.11
Summary: Basic ESRI ArcMap/ArcGis Pro TIE Toolbox to perform Trace Information Extraction (TIE) Analysis.
Author: swisstopo
Classifier: Development Status :: 3 - Alpha
Classifier: License :: OSI Approved :: BSD License
Classifier: Operating System :: Microsoft :: Windows
Classifier: Operating System :: POSIX :: Linux
Classifier: Topic :: Scientific/Engineering :: Image Processing
Classifier: Topic :: Scientific/Engineering :: GIS
Classifier: Programming Language :: Python
Classifier: Programming Language :: Python :: 3
Classifier: Programming Language :: Python :: 3.6
Classifier: Programming Language :: Python :: 3.7
Classifier: Programming Language :: Python :: 3.8
Classifier: Programming Language :: Python :: 3.9
Classifier: Programming Language :: Python :: 3.10
Classifier: Programming Language :: Python :: 3.11
Requires-Python: ~=3.9.18
License-File: LICENSE.txt
Requires-Dist: shapely
Requires-Dist: geocube
Requires-Dist: numpy
Requires-Dist: geopandas
Requires-Dist: mayavi
Requires-Dist: matplotlib
Requires-Dist: rasterio
Requires-Dist: scipy
Requires-Dist: scikit-image
Requires-Dist: dask
Requires-Dist: tqdm
Requires-Dist: gdal
Requires-Dist: pyproj
Requires-Dist: geojson
Requires-Dist: pyyaml
Requires-Dist: pyogrio
Requires-Dist: ipycytoscape
Requires-Dist: untie >=0.0.8
Requires-Dist: geocover-utils >=0.4.0
